confantic/__init__.py
confantic/__main__.py
confantic/editor.py
confantic/lib.py
confantic/validate.py
confantic-1.0.0.dist-info/METADATA
confantic-1.0.0.dist-info/WHEEL
confantic-1.0.0.dist-info/entry_points.txt
confantic-1.0.0.dist-info/top_level.txt
confantic-1.0.0.dist-info/RECORD
