Metadata-Version: 2.4
Name: confantic
Version: 1.0.0
Summary: A textual editor and validator for YAML/JSON files against Pydantic models.
Author-email: Kevin Welsh <kevin.welsh@verdantevolution.com>
Requires-Python: >=3.8
Requires-Dist: pydantic
Requires-Dist: pyyaml
Requires-Dist: textual[syntax]>=0.73.0
